grepg/__init__.py
grepg/command.py
grepg/grepg.py
grepg/main.py
grepg/model.py
grepg/util.py
grepg/subcommands/__init__.py
grepg/subcommands/configure.py
grepg/subcommands/create.py
grepg/subcommands/search.py
grepg/subcommands/show.py
grepg/subcommands/writer.py
grepg-1.0.1.dist-info/DESCRIPTION.rst
grepg-1.0.1.dist-info/METADATA
grepg-1.0.1.dist-info/RECORD
grepg-1.0.1.dist-info/WHEEL
grepg-1.0.1.dist-info/entry_points.txt
grepg-1.0.1.dist-info/metadata.json
grepg-1.0.1.dist-info/top_level.txt
tests/__init__.py
tests/grepg/__init__.py
tests/grepg/grepg_test.py
